astro_pest-0.1.0.dist-info/licenses/LICENSE
pest/__init__.py
pest/converter.py
pest/fits_converter.py
pest/gaia_converter.py
pest/preprocessing.py
pest/spherinator_data_preprocessing.py
astro_pest-0.1.0.dist-info/METADATA
astro_pest-0.1.0.dist-info/WHEEL
astro_pest-0.1.0.dist-info/top_level.txt
astro_pest-0.1.0.dist-info/RECORD
