Metadata-Version: 2.4
Name: astro-pest
Version: 0.1.0
Summary: Preprocessing Engine for Spherinator Training
Author-email: "Sebastian T. Gomez" <sebastian.trujillogomez@h-its.org>, Bernd Doser <bernd.doser@h-its.org>
License-Expression: Apache-2.0
Requires-Python: >=3.10
License-File: LICENSE
Requires-Dist: gaiaxpy>=2.1
Requires-Dist: h5py>=3.12
Requires-Dist: matplotlib>=3.10
Requires-Dist: pandas>=2.2
Requires-Dist: pyarrow>=20.0
Requires-Dist: pyyaml>=6.0
Requires-Dist: requests>=2.32
Requires-Dist: scikit-image>=0.25
Requires-Dist: scipy>=1.15
Provides-Extra: dev
Requires-Dist: ipykernel>=6.29; extra == "dev"
Requires-Dist: pytest>=8.3; extra == "dev"
Requires-Dist: ruff>=0.11.11; extra == "dev"
Dynamic: license-file
